socksx-0.1.1.dist-info/METADATA
socksx-0.1.1.dist-info/WHEEL
socksx/__init__.py
socksx/socksx.cpython-38-x86_64-linux-gnu.so
socksx-0.1.1.dist-info/RECORD
