Metadata-Version: 2.1
Name: socksx
Version: 0.1.1
Summary: A SOCKS toolkit for Python
Author: Onno Valkering
License: MIT
